idiotes/__init__.py
idiotes-0.0.1.dist-info/LICENSE
idiotes-0.0.1.dist-info/METADATA
idiotes-0.0.1.dist-info/WHEEL
idiotes-0.0.1.dist-info/top_level.txt
idiotes-0.0.1.dist-info/RECORD
