Metadata-Version: 2.1
Name: idiotes
Version: 0.0.1
Summary: ῐ̓δῐώτης • (idiṓtēs) - a private person, one not engaged in public affairs.
Author-email: Alexander Fedotov <alex.fedotov@aol.com>
Project-URL: Homepage, https://github.com/alxfed/idiotes
Project-URL: Bug Tracker, https://github.com/alxfed/idiotes/issues
Classifier: Programming Language :: Python :: 3
Classifier: License :: OSI Approved :: MIT License
Classifier: Operating System :: OS Independent
Requires-Python: >=3.10
License-File: LICENSE
